setup.py
src/ConfParse.py
src/RedisHelper.py
src/rabbitMQ.py
src/telecomcarrier_util.py
src/sms_util.egg-info/PKG-INFO
src/sms_util.egg-info/SOURCES.txt
src/sms_util.egg-info/dependency_links.txt
src/sms_util.egg-info/not-zip-safe
src/sms_util.egg-info/top_level.txt